coinmarketcap_scrapper/__init__.py
coinmarketcap_scrapper/__variables.py
coinmarketcap_scrapper/cmc_uteis.py
coinmarketcap_scrapper/coinmarketcap_scrapper.py
coinmarketcap_scrapper/dataclasses.py
coinmarketcap_scrapper/excepcions.py
coinmarketcap_scrapper/ligazons.db
coinmarketcap_scrapper-2.4.dist-info/LICENSE
coinmarketcap_scrapper-2.4.dist-info/METADATA
coinmarketcap_scrapper-2.4.dist-info/WHEEL
coinmarketcap_scrapper-2.4.dist-info/top_level.txt
coinmarketcap_scrapper-2.4.dist-info/RECORD
