Metadata-Version: 2.1
Name: coinmarketcap-scrapper
Version: 2.4
Summary: Scrapper of the CoinMarketCap website
Home-page: https://wwww.github.com/Ran-n/coinmarketcap_scrapper
Author: Ran#
Author-email: ran-n@tutanota.com
License: GPLv3
Project-URL: Bug Tracker, https://wwww.github.com/Ran-n/coinmarketcap_scrapper/issues
Platform: UNKNOWN
Classifier: Development Status :: 3 - Alpha
Classifier: Environment :: Console
Classifier: Intended Audience :: Developers
Classifier: License :: OSI Approved :: GNU General Public License v3 (GPLv3)
Classifier: Operating System :: OS Independent
Classifier: Programming Language :: Python :: 3.8
Classifier: Topic :: Software Development :: Libraries
Classifier: Topic :: Text Processing :: General
Classifier: Natural Language :: Galician
Classifier: Natural Language :: Portuguese
Classifier: Natural Language :: English
Classifier: Natural Language :: Spanish
Requires-Python: >=3.8.5
License-File: LICENSE
Requires-Dist: beautifulsoup4 (==4.10.0)
Requires-Dist: conexions (==1.3)
Requires-Dist: python-Levenshtein (==0.12.2)
Requires-Dist: uteis (==0.1.2.2)
